ROHSApy/__init__.py
ROHSApy/core.py
ROHSApy/init.py
ROHSApy-0.2.6.dist-info/LICENSE
ROHSApy-0.2.6.dist-info/METADATA
ROHSApy-0.2.6.dist-info/WHEEL
ROHSApy-0.2.6.dist-info/top_level.txt
ROHSApy-0.2.6.dist-info/RECORD
