Metadata-Version: 2.1
Name: ROHSApy
Version: 0.2.6
Summary: python interface package for ROHSA software
Home-page: https://github.com/antoinemarchal/ROHSA
Author: Antoine Marchal
Author-email: amarchal@cita.utoronto.ca
License: THE WORK (AS DEFINED BELOW) IS PROVIDED UNDER THE TERMS OF THIS CREATIVE COMMONS PUBLIC LICENSE ("CCPL" OR "LICENSE"). THE WORK IS PROTECTED BY COPYRIGHT AND/OR OTHER APPLICABLE LAW. ANY USE OF THE WORK OTHER THAN AS AUTHORIZED UNDER THIS LICENSE OR COPYRIGHT LAW IS PROHIBITED.
Requires-Dist: numpy
Requires-Dist: matplotlib
Requires-Dist: astropy
